{
    "menuCategories": [
      {
        "id": "grilled",
        "title": "Grilled",
        "items": [
          {
            "title": "Fish Grilled With Lemon Garlic Butter Sauce",
            "description": "Enjoy grilled fish pieces that we catch ourselves, boneless and carefully marinated with our special swefish marinade, covered in a delicious creamy sauce of fresh butter, refreshing lemon and rich local garlic flavour. We also offer extra lemon, butter and garlic sauce for free. Choose the appropriate weight of fish from this variety.",
            "price": 365,
            "image": "grilledLemonGarlic",
            "fullWidth": false,
            "isTopRated": false,
            "hasMultiplePrices": true,
            "weightOptions": [
              {
                "weight": "250 gm",
                "price": 365
              },
              {
                "weight": "500 gm",
                "price": 684
              },
              {
                "weight": "750 gm",
                "price": 1003
              },
              {
                "weight": "1 Kilo",
                "price": 1311
              }
            ]
          },
          {
            "title": "Grilled Shrimp with Lemon Garlic Butter Sauce",
            "description": "Enjoy grilled shrimp with a delicious creamy sauce of fresh butter, refreshing lemon, local garlic flavor and special Swish seasoning. We offer extra butter, garlic and lemon sauce for free. Choose the appropriate weight of shrimp from this variety.",
            "price": 319,
            "image": "grilledLemonGarlic",
            "fullWidth": false,
            "isTopRated": false,
            "hasMultiplePrices": true,
            "weightOptions": [
              {
                "weight": "200 gm Shrimp (6 Pieces)",
                "price": 319
              },
              {
                "weight": "300 gm Shrimp (8 Pieces)",
                "price": 399
              },
              {
                "weight": "1/2 Kilo Shrimp (16 Pieces)",
                "price": 718
              },
              {
                "weight": "1 Kilo Shrimp (32 Pieces)",
                "price": 1357
              }
            ]
          },
          {
            "title": "Fish Fillet Grilled With Olive Oil & Lemon",
            "description": "Enjoy the deliciousness of our own caught fish, boned and grilled with pure extra virgin olive oil and refreshing lemon juice. Suitable for Keto diet. Free portion of fresh grilled swefish vegetables seasoned with our special marinade. Choose the appropriate fish weight from this variety.",
            "image": "grilledOliveOil",
            "fullWidth": false,
            "isTopRated": false,
            "weightOptions": [
              {
                "weight": "250 gm",
                "price": 365
              },
              {
                "weight": "500 gm",
                "price": 684
              },
              {
                "weight": "750 gm",
                "price": 1003
              },
              {
                "weight": "1 Kilo",
                "price": 1311
              }
            ]
          },
          {
            "title": "Shrimp Grilled With Olive Oil & Lemon",
            "description": "Healthy and keto-friendly grilled shrimp with pure extra virgin olive oil and refreshing lemon juice. Free portion of fresh grilled swefish vegetables seasoned with our special seasoning. Choose the appropriate shrimp weight from this item.",
            "image": "grilledOliveOil",
            "fullWidth": false,
            "isTopRated": false,
            "weightOptions": [
              {
                "weight": "200 gm Shrimp (6 Pieces)",
                "price": 319.0
              },
              {
                "weight": "300 gm Shrimp (8 Pieces)",
                "price": 399.0
              },
              {
                "weight": "1/2 Kilo Shrimp (16 Pieces)",
                "price": 718.0
              },
              {
                "weight": "1 Kilo Shrimp (32 Pieces)",
                "price": 1357.0
              }
            ]
          }
        ]
      },
      {
        "id": "fish-chips",
        "title": "The Fish/Shrimp & Chips Meals",
        "items": [
          {
            "title": "The Fish & Chips",
            "description": "Indulge in golden-brown, crispy, wild-caught, fresh fish fillets served with our farm-grown potatoes and a selection of house-made sauces for free! Choose the desired fish weight.",
            "image": "fishAndChips",
            "fullWidth": false,
            "isTopRated": false,
            "weightOptions": [
              {
                "weight": "120 gm Fish Fillet (1 piece) + 2 Optional Sauces",
                "price": 222
              },
              {
                "weight": "250 gm Fish Fillet (2 pieces) + 2 Optional Sauces",
                "price": 410
              },
              {
                "weight": "480 gm Fish Fillet (4 pieces) + 4 Optional Sauces",
                "price": 775
              },
              {
                "weight": "1 Kilo Fish Fillet (8 pieces) + 4 Optional Sauces",
                "price": 1311
              }
            ]
          },
          {
            "title": "The Shrimp & Chips",
            "description": "Fresh butterfly shrimp, lightly battered and deep-fried to a perfect golden-brown, served with our farm grown potatoes and complimentary sauces. Choose your desired shrimp weight.",
            "image": "fishAndChips",
            "fullWidth": false,
            "isTopRated": false,
            "weightOptions": [
              {
                "weight": "200 gm Shrimp (6 Pieces) + 2 Optional Sauces",
                "price": 308
              },
              {
                "weight": "300 gm Shrimp (8 Pieces) + 2 Optional Sauces",
                "price": 399
              },
              {
                "weight": "1/2 Kilo Shrimp (16 Pieces) + 4 Optional Sauces",
                "price": 752
              },
              {
                "weight": "1 Kilo Shrimp (32 Pieces) + 4 Optional Sauces",
                "price": 1448
              }
            ]
          }
        ]
      },
      {
        "id": "fried",
        "title": "The Fried",
        "items": [
          {
            "title": "Fried Fish Fillet",
            "description": "Golden-brown, wild-caught, fresh crispy fish fillet, expertly seasoned and cooked to perfection. Free selection of house-made sauces. Choose desired fish weight.",
            "image": "friedFish",
            "fullWidth": false,
            "isTopRated": false,
            "weightOptions": [
              {
                "weight": "120 gm - 1 Piece",
                "price": 194
              },
              {
                "weight": "250 gm - 2 Pieces",
                "price": 342
              },
              {
                "weight": "480 gm - 4 Pieces",
                "price": 661
              },
              {
                "weight": "1 Kilo - 8 Pieces",
                "price": 1243
              }
            ]
          },
          {
            "title": "Fried Butterfly Shrimp",
            "description": "Crispy golden-brown butterfly fresh shrimp, prepared to perfection. Enjoy house-made sauces, crafted daily. Choose desired shrimp weight.",
            "image": "friedShrimpButterfly",
            "fullWidth": false,
            "isTopRated": false,
            "weightOptions": [
              {
                "weight": "200 gm Shrimp - 6 Pieces",
                "price": 296
              },
              {
                "weight": "300 gm Shrimp - 8 Pieces",
                "price": 376
              },
              {
                "weight": "1/2 Kilo Shrimp - 16 Pieces",
                "price": 707
              },
              {
                "weight": "1 Kilo Shrimp - 32 Pieces",
                "price": 1368
              }
            ]
          }
        ]
      },
      {
        "id": "soup",
        "title": "Soup",
        "items": [
          {
            "title": "Shrimp Bisque Soup",
            "description": "An aromatic shrimp broth infused with garlic, leeks, celery and swefish's special spices.",
            "price": 90,
            "image": "shrimpBisque",
            "fullWidth": false,
            "isTopRated": false
          }
        ]
      },
      {
        "id": "sandwiches",
        "title": "Sandwiches",
        "items": [
          {
            "title": "Jalapeño Mustard Crispy Fish Fillet",
            "description": "Crispy fish fillet meets fresh iceberg lettuce, pickled cucumbers, and jalapeno mustard sauce in fresh 5 oz round bread.",
            "price": 194,
            "image": "crispyFishSandwich",
            "fullWidth": false,
            "isTopRated": false
          }
        ]
      },
      {
        "id": "offers",
        "title": "Offers",
        "items": [
          {
            "title": "Offer 1",
            "description": "Jalapeno crispy fish fillet sandwich, fries packet and soft drink.",
            "oldPrice": 264,
            "price": 198,
            "image": "specialOffer",
            "fullWidth": false,
            "isTopRated": false
          }
        ]
      },
      {
        "id": "extras",
        "title": "Extras",
        "items": [
          {
            "title": "Fries Packet",
            "description": "Indulge in the crispiness of our chunky fries, cut from potatoes grown on our farms specifically for you and seasoned with SWEFISH's exclusive and unique spice blend.",
            "price": 45,
            "image": "fries",
            "fullWidth": false,
            "isTopRated": false
          },
          {
            "title": "Swefish Special Bread",
            "description": "Discover the taste of fresh white bread toasted with rich butter, aromatic local garlic, and fresh parsley.",
            "price": 10,
            "image": "specialBread",
            "fullWidth": false,
            "isTopRated": false
          },
          {
            "title": "SWEFISH Special Rice",
            "description": "Enjoy the delightful taste of our special rice, seasoned with a blend of our kitchen's secrets to complete your meal with a unique flavor.",
            "price": 57,
            "image": "specialRice",
            "fullWidth": false,
            "isTopRated": false
          },
          {
            "title": "SWEFISH Special Rice Large",
            "description": "Enjoy the delightful taste of our special rice, seasoned with a blend of our kitchen's secrets to complete your meal with a unique flavor.",
            "price": 78.66,
            "image": "specialRice",
            "fullWidth": false,
            "isTopRated": false
          },
          {
            "title": "Swefish Special Vegetables",
            "description": "Our grilled vegetables, seasoned with our special secret blend, including zucchini, carrots, bell peppers, and green beans.",
            "price": 55,
            "image": "specialVeggies",
            "fullWidth": false,
            "isTopRated": false
          }
        ]
      },
      {
        "id": "sauces",
        "title": "Sauces",
        "items": [
          {
            "title": "Lemon Garlic Butter Sauce (Medium)",
            "description": "A perfectly balanced and creamy sauce blending the refreshing taste of lemon with the rich depth of butter and the strong flavor of our local garlic.",
            "price": 45,
            "image": "lemonGarlicSauce",
            "fullWidth": false,
            "isTopRated": false
          },
          {
            "title": "Lemon Garlic Butter Sauce (Large)",
            "description": "A perfectly balanced and creamy sauce blending the refreshing taste of lemon with the rich depth of butter and the strong flavor of our local garlic.",
            "price": 75,
            "image": "lemonGarlicSauce",
            "fullWidth": false,
            "isTopRated": false
          },
          {
            "title": "Sweet Chili",
            "description": "Our house-made sweet chili sauce blends the perfect balance of sweetness and spice from red chili peppers, honey, and vinegar.",
            "price": 25,
            "image": "sweetChili",
            "fullWidth": false,
            "isTopRated": false
          },
          {
            "title": "Sriracha Tahini",
            "description": "Our tangy and creamy special sauce made with tahini, lemon juice, and a splash of sriracha red chili sauce for a spicy kick.",
            "price": 25,
            "image": "srirachaTahini",
            "fullWidth": false,
            "isTopRated": false
          },
          {
            "title": "Roquefort Sauce",
            "description": "A creamy and flavorful house-made blue cheese sauce, made with mayonnaise, salt, and freshly cracked black pepper.",
            "price": 25,
            "image": "roquefortSauce",
            "fullWidth": false,
            "isTopRated": false
          },
          {
            "title": "Cheddar Sauce",
            "description": "Our rich and buttery house-made cheddar sauce is crafted with local cheddar cheese and fresh milk.",
            "price": 25,
            "image": "cheddarSauce",
            "fullWidth": false,
            "isTopRated": false
          },
          {
            "title": "Honey Mustard",
            "description": "A sweet and tangy specialty dipping sauce made with mustard, honey, mayonnaise, and lemon juice.",
            "price": 25,
            "image": "honeyMustard",
            "fullWidth": false,
            "isTopRated": false
          },
          {
            "title": "Capers Tartar Sauce",
            "description": "A classic tartar sauce with a briny twist, featuring finely chopped pickled gherkins, sweet pickle relish, dill, and imported capers. Our in-house recipe is a unique take on a traditional favorite.",
            "price": 25,
            "image": "tartarSauce",
            "fullWidth": false,
            "isTopRated": false
          },
          {
            "title": "Barbecue Sauce",
            "description": "Smoked barbecue sauce.",
            "price": 25,
            "image": "barbecueSauce",
            "fullWidth": false,
            "isTopRated": false
          }
        ]
      },
      {
        "id": "salads",
        "title": "Salads",
        "items": [
          {
            "title": "Coleslaw",
            "description": "Our classic freshly made coleslaw features shredded white cabbage and carrots tossed in a creamy house-made mayonnaise-based dressing.",
            "price": 25,
            "image": "coleslaw",
            "fullWidth": false,
            "isTopRated": false
          },
          {
            "title": "Green Salad With Mustard Vinaigrette Dressing",
            "description": "Our refreshing green salad features a vibrant mix of cherry tomatoes, arugula, radish, and cucumber, tossed in our house-made mustard vinaigrette dressing — for free!",
            "price": 45,
            "image": "greenSalad",
            "fullWidth": false,
            "isTopRated": false
          }
        ]
      },
      {
        "id": "kids-meal",
        "title": "Kids Meal",
        "items": [
          {
            "title": "Kids Meal",
            "description": "Our freshly caught fish nuggets, prepared with the finest ingredients and deep-fried in pure oil, are served with our perfectly cooked farm-grown potatoes and a side of ketchup, making it an irresistible meal for kids.",
            "price": 150,
            "image": "kidsMeal",
            "fullWidth": false,
            "isTopRated": false
          }
        ]
      },
      {
        "id": "drinks",
        "title": "Drinks",
        "items": [
          {
            "title": "Pepsi",
            "description": "Pepsi Can 320ML",
            "price": 25,
            "image": "pepsi",
            "fullWidth": false,
            "isTopRated": false
          },
          {
            "title": "Mirinda Orange",
            "description": "Mirinda Orange Can 320ML",
            "price": 25,
            "image": "mirinda",
            "fullWidth": false,
            "isTopRated": false
          },
          {
            "title": "Mineral Water",
            "description": "600ML",
            "price": 13.68,
            "image": "mineralWater",
            "fullWidth": false,
            "isTopRated": false
          },
          {
            "title": "Birell Malt Drink Can",
            "description": "Birell non-alcoholic drink malt beverage.",
            "price": 35.34,
            "image": "birell",
            "fullWidth": false,
            "isTopRated": false
          }
        ]
      }
    ]
  }